pyproject_analyzer/__init__.py
pyproject_analyzer/main.py
pyproject_analyzer-0.0.3.dist-info/LICENCE
pyproject_analyzer-0.0.3.dist-info/METADATA
pyproject_analyzer-0.0.3.dist-info/WHEEL
pyproject_analyzer-0.0.3.dist-info/top_level.txt
pyproject_analyzer-0.0.3.dist-info/RECORD
