Metadata-Version: 2.1
Name: pyproject-analyzer
Version: 0.0.3
Summary: First module of PYCAudit (Python Code Audit) which aims to purpose an complet audit tool for Python Code
Home-page: http://mon_projet.org
Author: UNKNOWN
Author-email: UNKNOWN
License: UNKNOWN
Download-URL: http://packages.python.org/mon_projet
Keywords: project analyze audit setup.py
Platform: ALL
Classifier: Development Status :: 1 - Planning
Classifier: Environment :: Console
Classifier: Topic :: Software Development :: Documentation
Classifier: Topic :: Software Development :: Quality Assurance
Classifier: License :: OSI Approved :: MIT License
